web_python_builder/__init__.py
web_python_builder-0.1.dist-info/LICENSE.txt
web_python_builder-0.1.dist-info/METADATA
web_python_builder-0.1.dist-info/WHEEL
web_python_builder-0.1.dist-info/top_level.txt
web_python_builder-0.1.dist-info/RECORD
